gnnex/__init__.py
gnnex/config.py
gnnex/draw.py
gnnex/utils.py
gnnex-1.0.3.dist-info/LICENSE
gnnex-1.0.3.dist-info/METADATA
gnnex-1.0.3.dist-info/WHEEL
gnnex-1.0.3.dist-info/top_level.txt
gnnex-1.0.3.dist-info/RECORD
