Metadata-Version: 2.1
Name: gnnex
Version: 1.0.3
Summary: draw different colors to show edges' importance
Home-page: https://github.com/ifkid/gnnex
Author: Zhang Pin
Author-email: zhangpin@geetest.com
License: MIT LICENSE
Download-URL: https://pypi.org/manage/project/gnnexplainer/releases/
Platform: UNKNOWN
Classifier: Programming Language :: Python :: 3.7
Classifier: License :: OSI Approved :: MIT License
Classifier: Operating System :: OS Independent
Requires-Dist: keras (==2.3.1)
Requires-Dist: numpy (==1.17.2)
Requires-Dist: pandas (==0.25.3)
Requires-Dist: matplotlib (==3.1.1)
Requires-Dist: scipy (==1.3.2)
Requires-Dist: networkx (==2.2)
Requires-Dist: seaborn (==0.9.0)
